etcd_watcher/__init__.py
etcd_watcher/watcher.py
tests/__init__.py
tests/test_etcd_watcher.py
testtesttest0adasdasdasdasdasdssd0-1.0.0.dist-info/LICENSE
testtesttest0adasdasdasdasdasdssd0-1.0.0.dist-info/METADATA
testtesttest0adasdasdasdasdasdssd0-1.0.0.dist-info/WHEEL
testtesttest0adasdasdasdasdasdssd0-1.0.0.dist-info/top_level.txt
testtesttest0adasdasdasdasdasdssd0-1.0.0.dist-info/RECORD
