Metadata-Version: 2.1
Name: testtesttest0adasdasdasdasdasdssd0
Version: 1.0.0
Summary: Casbin role watcher to be used for monitoring updates to policies for PyCasbin
Author: nekotoxin
Author-email: nekotoxin@gmail.com
Classifier: Programming Language :: Python :: 3.6
Classifier: Programming Language :: Python :: 3.7
Classifier: Programming Language :: Python :: 3.8
Classifier: Programming Language :: Python :: 3.9
Classifier: License :: OSI Approved :: Apache Software License
License-File: LICENSE
